{
    "mappings": {
        "properties": {
            "book_id": {"type": "keyword"},
            "sec_0": {"type": "keyword"},
            "sec_1": {"type": "keyword"},
            "sec_2": {"type": "keyword"},
            "section_context": {"type": "keyword"},
            "doc_type": {"type": "keyword"},
            "content": {"type": "text"},
            "page_number": {"type": "integer"},
            "reading_order": {"type": "integer"},
            "image_metadata": {
                "type": "text",
                "index": false
            },
            "table_metadata": {
                "type": "text",
                "index": false
            },
            "vetor": {
                "type": "knn_vector",
                "dimension": -1,
                "method": {
                    "name": "hnsw",
                    "space_type": "cosinesimil",
                    "engine": "lucene",
                    "parameters": {
                        "ef_construction": 100,
                        "m": 16
                    }
                }
            }
        }
    },
    "settings": {
        "index.knn": true,
        "knn.algo_param.ef_search": 100,
        "number_of_shards": 2
    }
}



